{
  "$schema": "https://turborepo.org/schema.json",
  "pipeline": {
    "build": {
      "dependsOn": [
        "^build"
      ],
      "outputs": [
        ".svelte-kit/**",
        "dist/**",
        "build/**",
        "openapi.yaml",
        "./openapi.yaml"
      ]
    },
    "test": {
      "dependsOn": [
        "build"
      ],
      "outputs": [
        "playwright-report",
        "test-results"
      ],
      "cache": false
    },
    "dev": {
      "cache": false,
      "dependsOn": [
        "^build"
      ],
      "outputs": [
        ".svelte-kit/**",
        "dist/**",
        "build/**",
        "openapi.yaml"
      ]
    },
    "preview": {
      "dependsOn": [
        "build"
      ]
    },
    "@self/sdk#build": {
      "inputs": [
        "openapi.yaml"
      ],
      "outputs": [
        "src/**",
        "dist/**"
      ]
    },
    "preview:tunnel": {
      "dependsOn": [
        "build"
      ]
    }
  },
  "globalDependencies": [
    "**/.env",
    "**/.env.*",
    ".env"
  ]
}